pyfisheye/__init__.py
pyfisheye/calibration.py
pyfisheye/calibration_options.py
pyfisheye/calibration_result.py
pyfisheye/camera.py
pyfisheye/py.typed
pyfisheye/internal/__init__.py
pyfisheye/internal/projection.py
pyfisheye/internal/optimisation/__init__.py
pyfisheye/internal/optimisation/linear.py
pyfisheye/internal/optimisation/nonlinear.py
pyfisheye/internal/optimisation/optim_result.py
pyfisheye/internal/utils/__init__.py
pyfisheye/internal/utils/check_shapes.py
pyfisheye/internal/utils/common.py
pyfisheye/scripts/__init__.py
pyfisheye/scripts/calibrate.py
pyfisheye/scripts/demo.py
pyfisheye-1.0.1.dist-info/METADATA
pyfisheye-1.0.1.dist-info/WHEEL
pyfisheye-1.0.1.dist-info/RECORD
