Metadata-Version: 2.4
Name: pyfisheye
Version: 1.0.1
Summary: A Python / NumPy implementation of the omnidirectional camera model proposed by Scaramuzza et al.
Author-email: Joseph Agrane <josephagrane@gmail.com>
License-Expression: MIT
Requires-Python: >=3.10
Requires-Dist: matplotlib>=3.10.3
Requires-Dist: ndshapecheck>=0.2.2
Requires-Dist: numpy>=2.2.5
Requires-Dist: opencv-python>=4.11.0.86
Requires-Dist: pyqt6>=6.9.0
Requires-Dist: rich>=14.0.0
Requires-Dist: scipy>=1.15.3
Requires-Dist: tqdm>=4.67.1
